genesis_forge/__init__.py
genesis_forge/genesis_env.py
genesis_forge/managed_env.py
genesis_forge/utils.py
genesis_forge/gamepads/__init__.py
genesis_forge/gamepads/config.py
genesis_forge/gamepads/debug.py
genesis_forge/gamepads/gamepad.py
genesis_forge/gamepads/logitech.py
genesis_forge/managers/__init__.py
genesis_forge/managers/base.py
genesis_forge/managers/entity_manager.py
genesis_forge/managers/observation_manager.py
genesis_forge/managers/reward_manager.py
genesis_forge/managers/termination_manager.py
genesis_forge/managers/terrain_manager.py
genesis_forge/managers/action/__init__.py
genesis_forge/managers/action/base.py
genesis_forge/managers/action/position_action_manager.py
genesis_forge/managers/action/position_within_limits.py
genesis_forge/managers/actuator/__init__.py
genesis_forge/managers/actuator/actuator_manager.py
genesis_forge/managers/actuator/noisy_value.py
genesis_forge/managers/command/__init__.py
genesis_forge/managers/command/command_manager.py
genesis_forge/managers/command/velocity_command.py
genesis_forge/managers/config/__init__.py
genesis_forge/managers/config/config_item.py
genesis_forge/managers/config/mdp_fn_class.py
genesis_forge/managers/config/params_dict.py
genesis_forge/managers/contact/__init__.py
genesis_forge/managers/contact/config.py
genesis_forge/managers/contact/contact_manager.py
genesis_forge/managers/contact/kernel.py
genesis_forge/mdp/__init__.py
genesis_forge/mdp/observations.py
genesis_forge/mdp/reset.py
genesis_forge/mdp/rewards.py
genesis_forge/mdp/terminations.py
genesis_forge/values/__init__.py
genesis_forge/values/dof_value.py
genesis_forge/wrappers/__init__.py
genesis_forge/wrappers/rsl_rl.py
genesis_forge/wrappers/skrl.py
genesis_forge/wrappers/video.py
genesis_forge/wrappers/wrapper.py
genesis_forge-0.3.0.dist-info/METADATA
genesis_forge-0.3.0.dist-info/WHEEL
genesis_forge-0.3.0.dist-info/licenses/LICENSE
genesis_forge-0.3.0.dist-info/RECORD
