Metadata-Version: 2.4
Name: genesis-forge
Version: 0.3.0
Summary: A robotics RL training framework for Genesis inspired by Isaac Lab and Gymnasium.
Project-URL: Homepage, https://github.com/jgillick/genesis-forge
Project-URL: Issues, https://github.com/jgillick/genesis-forge/issues
Author: Jeremy Gillick
License-Expression: Apache-2.0
License-File: LICENSE
Classifier: Operating System :: OS Independent
Classifier: Programming Language :: Python :: 3
Requires-Python: >=3.10
Requires-Dist: deprecated
Requires-Dist: genesis-world>=0.3.4
Requires-Dist: gymnasium
Requires-Dist: hidapi
Requires-Dist: skrl[torch]
Requires-Dist: tensordict
Requires-Dist: torch
